{
  "id": "718e6f5e-5f8b-414d-9d0b-be34a467fdfe",
  "prevId": "2fabf0dc-ea6a-4055-ad21-4bdf7c6431de",
  "version": "7",
  "dialect": "postgresql",
  "tables": {
    "public.aggregator_account": {
      "name": "aggregator_account",
      "schema": "",
      "columns": {
        "id": {
          "name": "id",
          "type": "uuid",
          "primaryKey": true,
          "notNull": true,
          "default": "gen_random_uuid()"
        },
        "brand_id": {
          "name": "brand_id",
          "type": "uuid",
          "primaryKey": false,
          "notNull": true
        },
        "aggregator": {
          "name": "aggregator",
          "type": "aggregator",
          "typeSchema": "public",
          "primaryKey": false,
          "notNull": true
        },
        "external_merchant_id": {
          "name": "external_merchant_id",
          "type": "text",
          "primaryKey": false,
          "notNull": true
        },
        "credential_ref": {
          "name": "credential_ref",
          "type": "text",
          "primaryKey": false,
          "notNull": false
        },
        "is_active": {
          "name": "is_active",
          "type": "boolean",
          "primaryKey": false,
          "notNull": true,
          "default": true
        }
      },
      "indexes": {},
      "foreignKeys": {
        "aggregator_account_brand_id_brand_id_fk": {
          "name": "aggregator_account_brand_id_brand_id_fk",
          "tableFrom": "aggregator_account",
          "tableTo": "brand",
          "columnsFrom": [
            "brand_id"
          ],
          "columnsTo": [
            "id"
          ],
          "onDelete": "no action",
          "onUpdate": "no action"
        }
      },
      "compositePrimaryKeys": {},
      "uniqueConstraints": {},
      "policies": {},
      "checkConstraints": {},
      "isRLSEnabled": false
    },
    "public.attendance_record": {
      "name": "attendance_record",
      "schema": "",
      "columns": {
        "id": {
          "name": "id",
          "type": "uuid",
          "primaryKey": true,
          "notNull": true,
          "default": "gen_random_uuid()"
        },
        "employee_id": {
          "name": "employee_id",
          "type": "uuid",
          "primaryKey": false,
          "notNull": true
        },
        "type": {
          "name": "type",
          "type": "attendance_type",
          "typeSchema": "public",
          "primaryKey": false,
          "notNull": true
        },
        "photo_url": {
          "name": "photo_url",
          "type": "text",
          "primaryKey": false,
          "notNull": true
        },
        "photo_public_id": {
          "name": "photo_public_id",
          "type": "text",
          "primaryKey": false,
          "notNull": true
        },
        "captured_at": {
          "name": "captured_at",
          "type": "timestamp with time zone",
          "primaryKey": false,
          "notNull": true,
          "default": "now()"
        },
        "recorded_by_user_id": {
          "name": "recorded_by_user_id",
          "type": "uuid",
          "primaryKey": false,
          "notNull": true
        },
        "session_id": {
          "name": "session_id",
          "type": "uuid",
          "primaryKey": false,
          "notNull": false
        },
        "note": {
          "name": "note",
          "type": "text",
          "primaryKey": false,
          "notNull": false
        },
        "created_at": {
          "name": "created_at",
          "type": "timestamp with time zone",
          "primaryKey": false,
          "notNull": true,
          "default": "now()"
        }
      },
      "indexes": {},
      "foreignKeys": {
        "attendance_record_employee_id_employee_id_fk": {
          "name": "attendance_record_employee_id_employee_id_fk",
          "tableFrom": "attendance_record",
          "tableTo": "employee",
          "columnsFrom": [
            "employee_id"
          ],
          "columnsTo": [
            "id"
          ],
          "onDelete": "no action",
          "onUpdate": "no action"
        },
        "attendance_record_recorded_by_user_id_user_id_fk": {
          "name": "attendance_record_recorded_by_user_id_user_id_fk",
          "tableFrom": "attendance_record",
          "tableTo": "user",
          "columnsFrom": [
            "recorded_by_user_id"
          ],
          "columnsTo": [
            "id"
          ],
          "onDelete": "no action",
          "onUpdate": "no action"
        },
        "attendance_record_session_id_user_session_id_fk": {
          "name": "attendance_record_session_id_user_session_id_fk",
          "tableFrom": "attendance_record",
          "tableTo": "user_session",
          "columnsFrom": [
            "session_id"
          ],
          "columnsTo": [
            "id"
          ],
          "onDelete": "no action",
          "onUpdate": "no action"
        }
      },
      "compositePrimaryKeys": {},
      "uniqueConstraints": {},
      "policies": {},
      "checkConstraints": {},
      "isRLSEnabled": false
    },
    "public.audit_log": {
      "name": "audit_log",
      "schema": "",
      "columns": {
        "id": {
          "name": "id",
          "type": "uuid",
          "primaryKey": true,
          "notNull": true,
          "default": "gen_random_uuid()"
        },
        "actor_user_id": {
          "name": "actor_user_id",
          "type": "uuid",
          "primaryKey": false,
          "notNull": false
        },
        "actor_name": {
          "name": "actor_name",
          "type": "text",
          "primaryKey": false,
          "notNull": false
        },
        "session_id": {
          "name": "session_id",
          "type": "uuid",
          "primaryKey": false,
          "notNull": false
        },
        "action": {
          "name": "action",
          "type": "text",
          "primaryKey": false,
          "notNull": true
        },
        "description": {
          "name": "description",
          "type": "text",
          "primaryKey": false,
          "notNull": false
        },
        "entity_type": {
          "name": "entity_type",
          "type": "text",
          "primaryKey": false,
          "notNull": false
        },
        "entity_id": {
          "name": "entity_id",
          "type": "text",
          "primaryKey": false,
          "notNull": false
        },
        "metadata": {
          "name": "metadata",
          "type": "jsonb",
          "primaryKey": false,
          "notNull": false
        },
        "created_at": {
          "name": "created_at",
          "type": "timestamp with time zone",
          "primaryKey": false,
          "notNull": true,
          "default": "now()"
        }
      },
      "indexes": {},
      "foreignKeys": {
        "audit_log_actor_user_id_user_id_fk": {
          "name": "audit_log_actor_user_id_user_id_fk",
          "tableFrom": "audit_log",
          "tableTo": "user",
          "columnsFrom": [
            "actor_user_id"
          ],
          "columnsTo": [
            "id"
          ],
          "onDelete": "no action",
          "onUpdate": "no action"
        },
        "audit_log_session_id_user_session_id_fk": {
          "name": "audit_log_session_id_user_session_id_fk",
          "tableFrom": "audit_log",
          "tableTo": "user_session",
          "columnsFrom": [
            "session_id"
          ],
          "columnsTo": [
            "id"
          ],
          "onDelete": "no action",
          "onUpdate": "no action"
        }
      },
      "compositePrimaryKeys": {},
      "uniqueConstraints": {},
      "policies": {},
      "checkConstraints": {},
      "isRLSEnabled": false
    },
    "public.brand": {
      "name": "brand",
      "schema": "",
      "columns": {
        "id": {
          "name": "id",
          "type": "uuid",
          "primaryKey": true,
          "notNull": true,
          "default": "gen_random_uuid()"
        },
        "location_id": {
          "name": "location_id",
          "type": "uuid",
          "primaryKey": false,
          "notNull": true
        },
        "name": {
          "name": "name",
          "type": "text",
          "primaryKey": false,
          "notNull": true
        },
        "logo_url": {
          "name": "logo_url",
          "type": "text",
          "primaryKey": false,
          "notNull": false
        },
        "color": {
          "name": "color",
          "type": "text",
          "primaryKey": false,
          "notNull": true
        },
        "sales_perf_id": {
          "name": "sales_perf_id",
          "type": "text",
          "primaryKey": false,
          "notNull": true
        },
        "is_active": {
          "name": "is_active",
          "type": "boolean",
          "primaryKey": false,
          "notNull": true,
          "default": true
        }
      },
      "indexes": {},
      "foreignKeys": {
        "brand_location_id_location_id_fk": {
          "name": "brand_location_id_location_id_fk",
          "tableFrom": "brand",
          "tableTo": "location",
          "columnsFrom": [
            "location_id"
          ],
          "columnsTo": [
            "id"
          ],
          "onDelete": "no action",
          "onUpdate": "no action"
        }
      },
      "compositePrimaryKeys": {},
      "uniqueConstraints": {},
      "policies": {},
      "checkConstraints": {},
      "isRLSEnabled": false
    },
    "public.consumption_log": {
      "name": "consumption_log",
      "schema": "",
      "columns": {
        "id": {
          "name": "id",
          "type": "uuid",
          "primaryKey": true,
          "notNull": true,
          "default": "gen_random_uuid()"
        },
        "ingredient_id": {
          "name": "ingredient_id",
          "type": "uuid",
          "primaryKey": false,
          "notNull": true
        },
        "quantity": {
          "name": "quantity",
          "type": "numeric(14, 4)",
          "primaryKey": false,
          "notNull": true
        },
        "log_date": {
          "name": "log_date",
          "type": "timestamp with time zone",
          "primaryKey": false,
          "notNull": true,
          "default": "now()"
        },
        "logged_by": {
          "name": "logged_by",
          "type": "uuid",
          "primaryKey": false,
          "notNull": false
        },
        "order_id": {
          "name": "order_id",
          "type": "uuid",
          "primaryKey": false,
          "notNull": false
        }
      },
      "indexes": {},
      "foreignKeys": {
        "consumption_log_ingredient_id_ingredient_id_fk": {
          "name": "consumption_log_ingredient_id_ingredient_id_fk",
          "tableFrom": "consumption_log",
          "tableTo": "ingredient",
          "columnsFrom": [
            "ingredient_id"
          ],
          "columnsTo": [
            "id"
          ],
          "onDelete": "no action",
          "onUpdate": "no action"
        },
        "consumption_log_logged_by_user_id_fk": {
          "name": "consumption_log_logged_by_user_id_fk",
          "tableFrom": "consumption_log",
          "tableTo": "user",
          "columnsFrom": [
            "logged_by"
          ],
          "columnsTo": [
            "id"
          ],
          "onDelete": "no action",
          "onUpdate": "no action"
        },
        "consumption_log_order_id_order_id_fk": {
          "name": "consumption_log_order_id_order_id_fk",
          "tableFrom": "consumption_log",
          "tableTo": "order",
          "columnsFrom": [
            "order_id"
          ],
          "columnsTo": [
            "id"
          ],
          "onDelete": "no action",
          "onUpdate": "no action"
        }
      },
      "compositePrimaryKeys": {},
      "uniqueConstraints": {},
      "policies": {},
      "checkConstraints": {},
      "isRLSEnabled": false
    },
    "public.customer": {
      "name": "customer",
      "schema": "",
      "columns": {
        "id": {
          "name": "id",
          "type": "uuid",
          "primaryKey": true,
          "notNull": true,
          "default": "gen_random_uuid()"
        },
        "code": {
          "name": "code",
          "type": "text",
          "primaryKey": false,
          "notNull": true
        },
        "name": {
          "name": "name",
          "type": "text",
          "primaryKey": false,
          "notNull": true
        },
        "contact_name": {
          "name": "contact_name",
          "type": "text",
          "primaryKey": false,
          "notNull": false
        },
        "contact_phone": {
          "name": "contact_phone",
          "type": "text",
          "primaryKey": false,
          "notNull": false
        },
        "email": {
          "name": "email",
          "type": "text",
          "primaryKey": false,
          "notNull": false
        },
        "address": {
          "name": "address",
          "type": "text",
          "primaryKey": false,
          "notNull": false
        },
        "payment_term_days": {
          "name": "payment_term_days",
          "type": "integer",
          "primaryKey": false,
          "notNull": true,
          "default": 0
        },
        "is_active": {
          "name": "is_active",
          "type": "boolean",
          "primaryKey": false,
          "notNull": true,
          "default": true
        },
        "created_at": {
          "name": "created_at",
          "type": "timestamp with time zone",
          "primaryKey": false,
          "notNull": true,
          "default": "now()"
        },
        "updated_at": {
          "name": "updated_at",
          "type": "timestamp with time zone",
          "primaryKey": false,
          "notNull": true,
          "default": "now()"
        }
      },
      "indexes": {},
      "foreignKeys": {},
      "compositePrimaryKeys": {},
      "uniqueConstraints": {
        "customer_code_unique": {
          "name": "customer_code_unique",
          "nullsNotDistinct": false,
          "columns": [
            "code"
          ]
        }
      },
      "policies": {},
      "checkConstraints": {},
      "isRLSEnabled": false
    },
    "public.department_inventory_access": {
      "name": "department_inventory_access",
      "schema": "",
      "columns": {
        "id": {
          "name": "id",
          "type": "uuid",
          "primaryKey": true,
          "notNull": true,
          "default": "gen_random_uuid()"
        },
        "department": {
          "name": "department",
          "type": "department",
          "typeSchema": "public",
          "primaryKey": false,
          "notNull": true
        },
        "warehouse_type": {
          "name": "warehouse_type",
          "type": "warehouse_type",
          "typeSchema": "public",
          "primaryKey": false,
          "notNull": true
        },
        "can_view": {
          "name": "can_view",
          "type": "boolean",
          "primaryKey": false,
          "notNull": true,
          "default": true
        },
        "can_view_cost": {
          "name": "can_view_cost",
          "type": "boolean",
          "primaryKey": false,
          "notNull": true,
          "default": false
        },
        "can_receive": {
          "name": "can_receive",
          "type": "boolean",
          "primaryKey": false,
          "notNull": true,
          "default": false
        },
        "can_issue": {
          "name": "can_issue",
          "type": "boolean",
          "primaryKey": false,
          "notNull": true,
          "default": false
        },
        "can_adjust": {
          "name": "can_adjust",
          "type": "boolean",
          "primaryKey": false,
          "notNull": true,
          "default": false
        },
        "can_approve": {
          "name": "can_approve",
          "type": "boolean",
          "primaryKey": false,
          "notNull": true,
          "default": false
        },
        "updated_at": {
          "name": "updated_at",
          "type": "timestamp with time zone",
          "primaryKey": false,
          "notNull": true,
          "default": "now()"
        }
      },
      "indexes": {
        "department_inventory_access_unique": {
          "name": "department_inventory_access_unique",
          "columns": [
            {
              "expression": "department",
              "isExpression": false,
              "asc": true,
              "nulls": "last"
            },
            {
              "expression": "warehouse_type",
              "isExpression": false,
              "asc": true,
              "nulls": "last"
            }
          ],
          "isUnique": true,
          "concurrently": false,
          "method": "btree",
          "with": {}
        }
      },
      "foreignKeys": {},
      "compositePrimaryKeys": {},
      "uniqueConstraints": {},
      "policies": {},
      "checkConstraints": {},
      "isRLSEnabled": false
    },
    "public.employee": {
      "name": "employee",
      "schema": "",
      "columns": {
        "id": {
          "name": "id",
          "type": "uuid",
          "primaryKey": true,
          "notNull": true,
          "default": "gen_random_uuid()"
        },
        "user_id": {
          "name": "user_id",
          "type": "uuid",
          "primaryKey": false,
          "notNull": false
        },
        "employee_no": {
          "name": "employee_no",
          "type": "text",
          "primaryKey": false,
          "notNull": true
        },
        "full_name": {
          "name": "full_name",
          "type": "text",
          "primaryKey": false,
          "notNull": true
        },
        "department": {
          "name": "department",
          "type": "department",
          "typeSchema": "public",
          "primaryKey": false,
          "notNull": true
        },
        "position": {
          "name": "position",
          "type": "text",
          "primaryKey": false,
          "notNull": false
        },
        "photo_url": {
          "name": "photo_url",
          "type": "text",
          "primaryKey": false,
          "notNull": false
        },
        "status": {
          "name": "status",
          "type": "employee_status",
          "typeSchema": "public",
          "primaryKey": false,
          "notNull": true,
          "default": "'ACTIVE'"
        },
        "created_at": {
          "name": "created_at",
          "type": "timestamp with time zone",
          "primaryKey": false,
          "notNull": true,
          "default": "now()"
        },
        "updated_at": {
          "name": "updated_at",
          "type": "timestamp with time zone",
          "primaryKey": false,
          "notNull": true,
          "default": "now()"
        }
      },
      "indexes": {},
      "foreignKeys": {
        "employee_user_id_user_id_fk": {
          "name": "employee_user_id_user_id_fk",
          "tableFrom": "employee",
          "tableTo": "user",
          "columnsFrom": [
            "user_id"
          ],
          "columnsTo": [
            "id"
          ],
          "onDelete": "no action",
          "onUpdate": "no action"
        }
      },
      "compositePrimaryKeys": {},
      "uniqueConstraints": {
        "employee_employee_no_unique": {
          "name": "employee_employee_no_unique",
          "nullsNotDistinct": false,
          "columns": [
            "employee_no"
          ]
        }
      },
      "policies": {},
      "checkConstraints": {},
      "isRLSEnabled": false
    },
    "public.ingredient": {
      "name": "ingredient",
      "schema": "",
      "columns": {
        "id": {
          "name": "id",
          "type": "uuid",
          "primaryKey": true,
          "notNull": true,
          "default": "gen_random_uuid()"
        },
        "name": {
          "name": "name",
          "type": "text",
          "primaryKey": false,
          "notNull": true
        },
        "unit": {
          "name": "unit",
          "type": "text",
          "primaryKey": false,
          "notNull": true
        },
        "unit_cost": {
          "name": "unit_cost",
          "type": "numeric(14, 4)",
          "primaryKey": false,
          "notNull": true
        },
        "low_stock_threshold": {
          "name": "low_stock_threshold",
          "type": "numeric(14, 4)",
          "primaryKey": false,
          "notNull": true
        }
      },
      "indexes": {},
      "foreignKeys": {},
      "compositePrimaryKeys": {},
      "uniqueConstraints": {},
      "policies": {},
      "checkConstraints": {},
      "isRLSEnabled": false
    },
    "public.inventory_stock": {
      "name": "inventory_stock",
      "schema": "",
      "columns": {
        "id": {
          "name": "id",
          "type": "uuid",
          "primaryKey": true,
          "notNull": true,
          "default": "gen_random_uuid()"
        },
        "warehouse_id": {
          "name": "warehouse_id",
          "type": "uuid",
          "primaryKey": false,
          "notNull": true
        },
        "ingredient_id": {
          "name": "ingredient_id",
          "type": "uuid",
          "primaryKey": false,
          "notNull": true
        },
        "quantity": {
          "name": "quantity",
          "type": "numeric(14, 4)",
          "primaryKey": false,
          "notNull": true,
          "default": "'0'"
        }
      },
      "indexes": {
        "inventory_stock_warehouse_ingredient_unique": {
          "name": "inventory_stock_warehouse_ingredient_unique",
          "columns": [
            {
              "expression": "warehouse_id",
              "isExpression": false,
              "asc": true,
              "nulls": "last"
            },
            {
              "expression": "ingredient_id",
              "isExpression": false,
              "asc": true,
              "nulls": "last"
            }
          ],
          "isUnique": true,
          "concurrently": false,
          "method": "btree",
          "with": {}
        }
      },
      "foreignKeys": {
        "inventory_stock_warehouse_id_warehouse_id_fk": {
          "name": "inventory_stock_warehouse_id_warehouse_id_fk",
          "tableFrom": "inventory_stock",
          "tableTo": "warehouse",
          "columnsFrom": [
            "warehouse_id"
          ],
          "columnsTo": [
            "id"
          ],
          "onDelete": "no action",
          "onUpdate": "no action"
        },
        "inventory_stock_ingredient_id_ingredient_id_fk": {
          "name": "inventory_stock_ingredient_id_ingredient_id_fk",
          "tableFrom": "inventory_stock",
          "tableTo": "ingredient",
          "columnsFrom": [
            "ingredient_id"
          ],
          "columnsTo": [
            "id"
          ],
          "onDelete": "no action",
          "onUpdate": "no action"
        }
      },
      "compositePrimaryKeys": {},
      "uniqueConstraints": {},
      "policies": {},
      "checkConstraints": {},
      "isRLSEnabled": false
    },
    "public.ito_item": {
      "name": "ito_item",
      "schema": "",
      "columns": {
        "id": {
          "name": "id",
          "type": "uuid",
          "primaryKey": true,
          "notNull": true,
          "default": "gen_random_uuid()"
        },
        "ito_id": {
          "name": "ito_id",
          "type": "uuid",
          "primaryKey": false,
          "notNull": true
        },
        "ingredient_id": {
          "name": "ingredient_id",
          "type": "uuid",
          "primaryKey": false,
          "notNull": true
        },
        "quantity": {
          "name": "quantity",
          "type": "numeric(14, 4)",
          "primaryKey": false,
          "notNull": true
        }
      },
      "indexes": {},
      "foreignKeys": {
        "ito_item_ito_id_ito_id_fk": {
          "name": "ito_item_ito_id_ito_id_fk",
          "tableFrom": "ito_item",
          "tableTo": "ito",
          "columnsFrom": [
            "ito_id"
          ],
          "columnsTo": [
            "id"
          ],
          "onDelete": "no action",
          "onUpdate": "no action"
        },
        "ito_item_ingredient_id_ingredient_id_fk": {
          "name": "ito_item_ingredient_id_ingredient_id_fk",
          "tableFrom": "ito_item",
          "tableTo": "ingredient",
          "columnsFrom": [
            "ingredient_id"
          ],
          "columnsTo": [
            "id"
          ],
          "onDelete": "no action",
          "onUpdate": "no action"
        }
      },
      "compositePrimaryKeys": {},
      "uniqueConstraints": {},
      "policies": {},
      "checkConstraints": {},
      "isRLSEnabled": false
    },
    "public.ito": {
      "name": "ito",
      "schema": "",
      "columns": {
        "id": {
          "name": "id",
          "type": "uuid",
          "primaryKey": true,
          "notNull": true,
          "default": "gen_random_uuid()"
        },
        "from_warehouse_id": {
          "name": "from_warehouse_id",
          "type": "uuid",
          "primaryKey": false,
          "notNull": true
        },
        "to_warehouse_id": {
          "name": "to_warehouse_id",
          "type": "uuid",
          "primaryKey": false,
          "notNull": true
        },
        "status": {
          "name": "status",
          "type": "ito_status",
          "typeSchema": "public",
          "primaryKey": false,
          "notNull": true,
          "default": "'REQUESTED'"
        },
        "requested_by": {
          "name": "requested_by",
          "type": "uuid",
          "primaryKey": false,
          "notNull": false
        },
        "confirmed_by": {
          "name": "confirmed_by",
          "type": "uuid",
          "primaryKey": false,
          "notNull": false
        },
        "created_at": {
          "name": "created_at",
          "type": "timestamp with time zone",
          "primaryKey": false,
          "notNull": true,
          "default": "now()"
        },
        "confirmed_at": {
          "name": "confirmed_at",
          "type": "timestamp with time zone",
          "primaryKey": false,
          "notNull": false
        }
      },
      "indexes": {},
      "foreignKeys": {
        "ito_from_warehouse_id_warehouse_id_fk": {
          "name": "ito_from_warehouse_id_warehouse_id_fk",
          "tableFrom": "ito",
          "tableTo": "warehouse",
          "columnsFrom": [
            "from_warehouse_id"
          ],
          "columnsTo": [
            "id"
          ],
          "onDelete": "no action",
          "onUpdate": "no action"
        },
        "ito_to_warehouse_id_warehouse_id_fk": {
          "name": "ito_to_warehouse_id_warehouse_id_fk",
          "tableFrom": "ito",
          "tableTo": "warehouse",
          "columnsFrom": [
            "to_warehouse_id"
          ],
          "columnsTo": [
            "id"
          ],
          "onDelete": "no action",
          "onUpdate": "no action"
        },
        "ito_requested_by_user_id_fk": {
          "name": "ito_requested_by_user_id_fk",
          "tableFrom": "ito",
          "tableTo": "user",
          "columnsFrom": [
            "requested_by"
          ],
          "columnsTo": [
            "id"
          ],
          "onDelete": "no action",
          "onUpdate": "no action"
        },
        "ito_confirmed_by_user_id_fk": {
          "name": "ito_confirmed_by_user_id_fk",
          "tableFrom": "ito",
          "tableTo": "user",
          "columnsFrom": [
            "confirmed_by"
          ],
          "columnsTo": [
            "id"
          ],
          "onDelete": "no action",
          "onUpdate": "no action"
        }
      },
      "compositePrimaryKeys": {},
      "uniqueConstraints": {},
      "policies": {},
      "checkConstraints": {},
      "isRLSEnabled": false
    },
    "public.kitchen_station": {
      "name": "kitchen_station",
      "schema": "",
      "columns": {
        "id": {
          "name": "id",
          "type": "uuid",
          "primaryKey": true,
          "notNull": true,
          "default": "gen_random_uuid()"
        },
        "location_id": {
          "name": "location_id",
          "type": "uuid",
          "primaryKey": false,
          "notNull": true
        },
        "name": {
          "name": "name",
          "type": "text",
          "primaryKey": false,
          "notNull": true
        },
        "default_printer_id": {
          "name": "default_printer_id",
          "type": "uuid",
          "primaryKey": false,
          "notNull": false
        }
      },
      "indexes": {},
      "foreignKeys": {
        "kitchen_station_location_id_location_id_fk": {
          "name": "kitchen_station_location_id_location_id_fk",
          "tableFrom": "kitchen_station",
          "tableTo": "location",
          "columnsFrom": [
            "location_id"
          ],
          "columnsTo": [
            "id"
          ],
          "onDelete": "no action",
          "onUpdate": "no action"
        },
        "kitchen_station_default_printer_id_printer_id_fk": {
          "name": "kitchen_station_default_printer_id_printer_id_fk",
          "tableFrom": "kitchen_station",
          "tableTo": "printer",
          "columnsFrom": [
            "default_printer_id"
          ],
          "columnsTo": [
            "id"
          ],
          "onDelete": "no action",
          "onUpdate": "no action"
        }
      },
      "compositePrimaryKeys": {},
      "uniqueConstraints": {},
      "policies": {},
      "checkConstraints": {},
      "isRLSEnabled": false
    },
    "public.location": {
      "name": "location",
      "schema": "",
      "columns": {
        "id": {
          "name": "id",
          "type": "uuid",
          "primaryKey": true,
          "notNull": true,
          "default": "gen_random_uuid()"
        },
        "code": {
          "name": "code",
          "type": "text",
          "primaryKey": false,
          "notNull": true
        },
        "name": {
          "name": "name",
          "type": "text",
          "primaryKey": false,
          "notNull": true
        },
        "address": {
          "name": "address",
          "type": "text",
          "primaryKey": false,
          "notNull": false
        },
        "status": {
          "name": "status",
          "type": "location_status",
          "typeSchema": "public",
          "primaryKey": false,
          "notNull": true,
          "default": "'ACTIVE'"
        },
        "timezone": {
          "name": "timezone",
          "type": "text",
          "primaryKey": false,
          "notNull": true,
          "default": "'Asia/Manila'"
        },
        "contact_name": {
          "name": "contact_name",
          "type": "text",
          "primaryKey": false,
          "notNull": false
        },
        "contact_phone": {
          "name": "contact_phone",
          "type": "text",
          "primaryKey": false,
          "notNull": false
        }
      },
      "indexes": {
        "location_code_unique": {
          "name": "location_code_unique",
          "columns": [
            {
              "expression": "code",
              "isExpression": false,
              "asc": true,
              "nulls": "last"
            }
          ],
          "isUnique": true,
          "concurrently": false,
          "method": "btree",
          "with": {}
        }
      },
      "foreignKeys": {},
      "compositePrimaryKeys": {},
      "uniqueConstraints": {},
      "policies": {},
      "checkConstraints": {},
      "isRLSEnabled": false
    },
    "public.menu_item": {
      "name": "menu_item",
      "schema": "",
      "columns": {
        "id": {
          "name": "id",
          "type": "uuid",
          "primaryKey": true,
          "notNull": true,
          "default": "gen_random_uuid()"
        },
        "brand_id": {
          "name": "brand_id",
          "type": "uuid",
          "primaryKey": false,
          "notNull": true
        },
        "name": {
          "name": "name",
          "type": "text",
          "primaryKey": false,
          "notNull": true
        },
        "price": {
          "name": "price",
          "type": "numeric(14, 2)",
          "primaryKey": false,
          "notNull": true
        },
        "prep_time_min": {
          "name": "prep_time_min",
          "type": "integer",
          "primaryKey": false,
          "notNull": false
        },
        "station_id": {
          "name": "station_id",
          "type": "uuid",
          "primaryKey": false,
          "notNull": false
        },
        "availability": {
          "name": "availability",
          "type": "availability",
          "typeSchema": "public",
          "primaryKey": false,
          "notNull": true,
          "default": "'AVAILABLE'"
        }
      },
      "indexes": {},
      "foreignKeys": {
        "menu_item_brand_id_brand_id_fk": {
          "name": "menu_item_brand_id_brand_id_fk",
          "tableFrom": "menu_item",
          "tableTo": "brand",
          "columnsFrom": [
            "brand_id"
          ],
          "columnsTo": [
            "id"
          ],
          "onDelete": "no action",
          "onUpdate": "no action"
        },
        "menu_item_station_id_kitchen_station_id_fk": {
          "name": "menu_item_station_id_kitchen_station_id_fk",
          "tableFrom": "menu_item",
          "tableTo": "kitchen_station",
          "columnsFrom": [
            "station_id"
          ],
          "columnsTo": [
            "id"
          ],
          "onDelete": "no action",
          "onUpdate": "no action"
        }
      },
      "compositePrimaryKeys": {},
      "uniqueConstraints": {},
      "policies": {},
      "checkConstraints": {},
      "isRLSEnabled": false
    },
    "public.order_item": {
      "name": "order_item",
      "schema": "",
      "columns": {
        "id": {
          "name": "id",
          "type": "uuid",
          "primaryKey": true,
          "notNull": true,
          "default": "gen_random_uuid()"
        },
        "order_id": {
          "name": "order_id",
          "type": "uuid",
          "primaryKey": false,
          "notNull": true
        },
        "menu_item_id": {
          "name": "menu_item_id",
          "type": "uuid",
          "primaryKey": false,
          "notNull": true
        },
        "qty": {
          "name": "qty",
          "type": "integer",
          "primaryKey": false,
          "notNull": true
        },
        "station_id": {
          "name": "station_id",
          "type": "uuid",
          "primaryKey": false,
          "notNull": true
        },
        "notes": {
          "name": "notes",
          "type": "text",
          "primaryKey": false,
          "notNull": false
        }
      },
      "indexes": {},
      "foreignKeys": {
        "order_item_order_id_order_id_fk": {
          "name": "order_item_order_id_order_id_fk",
          "tableFrom": "order_item",
          "tableTo": "order",
          "columnsFrom": [
            "order_id"
          ],
          "columnsTo": [
            "id"
          ],
          "onDelete": "no action",
          "onUpdate": "no action"
        },
        "order_item_menu_item_id_menu_item_id_fk": {
          "name": "order_item_menu_item_id_menu_item_id_fk",
          "tableFrom": "order_item",
          "tableTo": "menu_item",
          "columnsFrom": [
            "menu_item_id"
          ],
          "columnsTo": [
            "id"
          ],
          "onDelete": "no action",
          "onUpdate": "no action"
        },
        "order_item_station_id_kitchen_station_id_fk": {
          "name": "order_item_station_id_kitchen_station_id_fk",
          "tableFrom": "order_item",
          "tableTo": "kitchen_station",
          "columnsFrom": [
            "station_id"
          ],
          "columnsTo": [
            "id"
          ],
          "onDelete": "no action",
          "onUpdate": "no action"
        }
      },
      "compositePrimaryKeys": {},
      "uniqueConstraints": {},
      "policies": {},
      "checkConstraints": {},
      "isRLSEnabled": false
    },
    "public.order": {
      "name": "order",
      "schema": "",
      "columns": {
        "id": {
          "name": "id",
          "type": "uuid",
          "primaryKey": true,
          "notNull": true,
          "default": "gen_random_uuid()"
        },
        "brand_id": {
          "name": "brand_id",
          "type": "uuid",
          "primaryKey": false,
          "notNull": true
        },
        "aggregator_account_id": {
          "name": "aggregator_account_id",
          "type": "uuid",
          "primaryKey": false,
          "notNull": true
        },
        "aggregator": {
          "name": "aggregator",
          "type": "aggregator",
          "typeSchema": "public",
          "primaryKey": false,
          "notNull": true
        },
        "external_ref": {
          "name": "external_ref",
          "type": "text",
          "primaryKey": false,
          "notNull": true
        },
        "customer_name": {
          "name": "customer_name",
          "type": "text",
          "primaryKey": false,
          "notNull": false
        },
        "status": {
          "name": "status",
          "type": "order_status",
          "typeSchema": "public",
          "primaryKey": false,
          "notNull": true,
          "default": "'NEW'"
        },
        "total": {
          "name": "total",
          "type": "numeric(14, 2)",
          "primaryKey": false,
          "notNull": true
        },
        "placed_at": {
          "name": "placed_at",
          "type": "timestamp with time zone",
          "primaryKey": false,
          "notNull": true,
          "default": "now()"
        },
        "prep_at": {
          "name": "prep_at",
          "type": "timestamp with time zone",
          "primaryKey": false,
          "notNull": false
        },
        "ready_at": {
          "name": "ready_at",
          "type": "timestamp with time zone",
          "primaryKey": false,
          "notNull": false
        },
        "completed_at": {
          "name": "completed_at",
          "type": "timestamp with time zone",
          "primaryKey": false,
          "notNull": false
        },
        "created_at": {
          "name": "created_at",
          "type": "timestamp with time zone",
          "primaryKey": false,
          "notNull": true,
          "default": "now()"
        },
        "updated_at": {
          "name": "updated_at",
          "type": "timestamp with time zone",
          "primaryKey": false,
          "notNull": true,
          "default": "now()"
        }
      },
      "indexes": {
        "order_aggregator_external_ref_unique": {
          "name": "order_aggregator_external_ref_unique",
          "columns": [
            {
              "expression": "aggregator",
              "isExpression": false,
              "asc": true,
              "nulls": "last"
            },
            {
              "expression": "external_ref",
              "isExpression": false,
              "asc": true,
              "nulls": "last"
            }
          ],
          "isUnique": true,
          "concurrently": false,
          "method": "btree",
          "with": {}
        }
      },
      "foreignKeys": {
        "order_brand_id_brand_id_fk": {
          "name": "order_brand_id_brand_id_fk",
          "tableFrom": "order",
          "tableTo": "brand",
          "columnsFrom": [
            "brand_id"
          ],
          "columnsTo": [
            "id"
          ],
          "onDelete": "no action",
          "onUpdate": "no action"
        },
        "order_aggregator_account_id_aggregator_account_id_fk": {
          "name": "order_aggregator_account_id_aggregator_account_id_fk",
          "tableFrom": "order",
          "tableTo": "aggregator_account",
          "columnsFrom": [
            "aggregator_account_id"
          ],
          "columnsTo": [
            "id"
          ],
          "onDelete": "no action",
          "onUpdate": "no action"
        }
      },
      "compositePrimaryKeys": {},
      "uniqueConstraints": {},
      "policies": {},
      "checkConstraints": {},
      "isRLSEnabled": false
    },
    "public.print_agent": {
      "name": "print_agent",
      "schema": "",
      "columns": {
        "id": {
          "name": "id",
          "type": "uuid",
          "primaryKey": true,
          "notNull": true,
          "default": "gen_random_uuid()"
        },
        "location_id": {
          "name": "location_id",
          "type": "uuid",
          "primaryKey": false,
          "notNull": true
        },
        "api_token": {
          "name": "api_token",
          "type": "text",
          "primaryKey": false,
          "notNull": true
        },
        "name": {
          "name": "name",
          "type": "text",
          "primaryKey": false,
          "notNull": false
        },
        "last_seen": {
          "name": "last_seen",
          "type": "timestamp with time zone",
          "primaryKey": false,
          "notNull": false
        }
      },
      "indexes": {},
      "foreignKeys": {
        "print_agent_location_id_location_id_fk": {
          "name": "print_agent_location_id_location_id_fk",
          "tableFrom": "print_agent",
          "tableTo": "location",
          "columnsFrom": [
            "location_id"
          ],
          "columnsTo": [
            "id"
          ],
          "onDelete": "no action",
          "onUpdate": "no action"
        }
      },
      "compositePrimaryKeys": {},
      "uniqueConstraints": {},
      "policies": {},
      "checkConstraints": {},
      "isRLSEnabled": false
    },
    "public.print_job": {
      "name": "print_job",
      "schema": "",
      "columns": {
        "id": {
          "name": "id",
          "type": "uuid",
          "primaryKey": true,
          "notNull": true,
          "default": "gen_random_uuid()"
        },
        "order_id": {
          "name": "order_id",
          "type": "uuid",
          "primaryKey": false,
          "notNull": true
        },
        "station_id": {
          "name": "station_id",
          "type": "uuid",
          "primaryKey": false,
          "notNull": true
        },
        "printer_id": {
          "name": "printer_id",
          "type": "uuid",
          "primaryKey": false,
          "notNull": false
        },
        "payload": {
          "name": "payload",
          "type": "jsonb",
          "primaryKey": false,
          "notNull": true
        },
        "status": {
          "name": "status",
          "type": "print_job_status",
          "typeSchema": "public",
          "primaryKey": false,
          "notNull": true,
          "default": "'PENDING'"
        },
        "error": {
          "name": "error",
          "type": "text",
          "primaryKey": false,
          "notNull": false
        },
        "retries": {
          "name": "retries",
          "type": "integer",
          "primaryKey": false,
          "notNull": true,
          "default": 0
        },
        "created_at": {
          "name": "created_at",
          "type": "timestamp with time zone",
          "primaryKey": false,
          "notNull": true,
          "default": "now()"
        },
        "printed_at": {
          "name": "printed_at",
          "type": "timestamp with time zone",
          "primaryKey": false,
          "notNull": false
        }
      },
      "indexes": {},
      "foreignKeys": {
        "print_job_order_id_order_id_fk": {
          "name": "print_job_order_id_order_id_fk",
          "tableFrom": "print_job",
          "tableTo": "order",
          "columnsFrom": [
            "order_id"
          ],
          "columnsTo": [
            "id"
          ],
          "onDelete": "no action",
          "onUpdate": "no action"
        },
        "print_job_station_id_kitchen_station_id_fk": {
          "name": "print_job_station_id_kitchen_station_id_fk",
          "tableFrom": "print_job",
          "tableTo": "kitchen_station",
          "columnsFrom": [
            "station_id"
          ],
          "columnsTo": [
            "id"
          ],
          "onDelete": "no action",
          "onUpdate": "no action"
        },
        "print_job_printer_id_printer_id_fk": {
          "name": "print_job_printer_id_printer_id_fk",
          "tableFrom": "print_job",
          "tableTo": "printer",
          "columnsFrom": [
            "printer_id"
          ],
          "columnsTo": [
            "id"
          ],
          "onDelete": "no action",
          "onUpdate": "no action"
        }
      },
      "compositePrimaryKeys": {},
      "uniqueConstraints": {},
      "policies": {},
      "checkConstraints": {},
      "isRLSEnabled": false
    },
    "public.printer": {
      "name": "printer",
      "schema": "",
      "columns": {
        "id": {
          "name": "id",
          "type": "uuid",
          "primaryKey": true,
          "notNull": true,
          "default": "gen_random_uuid()"
        },
        "name": {
          "name": "name",
          "type": "text",
          "primaryKey": false,
          "notNull": true
        },
        "connection": {
          "name": "connection",
          "type": "printer_connection",
          "typeSchema": "public",
          "primaryKey": false,
          "notNull": true
        },
        "address": {
          "name": "address",
          "type": "text",
          "primaryKey": false,
          "notNull": true
        },
        "status": {
          "name": "status",
          "type": "printer_status",
          "typeSchema": "public",
          "primaryKey": false,
          "notNull": true,
          "default": "'OFFLINE'"
        },
        "last_seen": {
          "name": "last_seen",
          "type": "timestamp with time zone",
          "primaryKey": false,
          "notNull": false
        }
      },
      "indexes": {},
      "foreignKeys": {},
      "compositePrimaryKeys": {},
      "uniqueConstraints": {},
      "policies": {},
      "checkConstraints": {},
      "isRLSEnabled": false
    },
    "public.purchase_order_line": {
      "name": "purchase_order_line",
      "schema": "",
      "columns": {
        "id": {
          "name": "id",
          "type": "uuid",
          "primaryKey": true,
          "notNull": true,
          "default": "gen_random_uuid()"
        },
        "po_id": {
          "name": "po_id",
          "type": "uuid",
          "primaryKey": false,
          "notNull": true
        },
        "ingredient_id": {
          "name": "ingredient_id",
          "type": "uuid",
          "primaryKey": false,
          "notNull": true
        },
        "quantity": {
          "name": "quantity",
          "type": "numeric(14, 4)",
          "primaryKey": false,
          "notNull": true
        },
        "unit_cost": {
          "name": "unit_cost",
          "type": "numeric(14, 4)",
          "primaryKey": false,
          "notNull": true,
          "default": "'0'"
        },
        "qty_received": {
          "name": "qty_received",
          "type": "numeric(14, 4)",
          "primaryKey": false,
          "notNull": true,
          "default": "'0'"
        }
      },
      "indexes": {},
      "foreignKeys": {
        "purchase_order_line_po_id_purchase_order_id_fk": {
          "name": "purchase_order_line_po_id_purchase_order_id_fk",
          "tableFrom": "purchase_order_line",
          "tableTo": "purchase_order",
          "columnsFrom": [
            "po_id"
          ],
          "columnsTo": [
            "id"
          ],
          "onDelete": "no action",
          "onUpdate": "no action"
        },
        "purchase_order_line_ingredient_id_ingredient_id_fk": {
          "name": "purchase_order_line_ingredient_id_ingredient_id_fk",
          "tableFrom": "purchase_order_line",
          "tableTo": "ingredient",
          "columnsFrom": [
            "ingredient_id"
          ],
          "columnsTo": [
            "id"
          ],
          "onDelete": "no action",
          "onUpdate": "no action"
        }
      },
      "compositePrimaryKeys": {},
      "uniqueConstraints": {},
      "policies": {},
      "checkConstraints": {},
      "isRLSEnabled": false
    },
    "public.purchase_order": {
      "name": "purchase_order",
      "schema": "",
      "columns": {
        "id": {
          "name": "id",
          "type": "uuid",
          "primaryKey": true,
          "notNull": true,
          "default": "gen_random_uuid()"
        },
        "po_no": {
          "name": "po_no",
          "type": "text",
          "primaryKey": false,
          "notNull": true
        },
        "supplier_id": {
          "name": "supplier_id",
          "type": "uuid",
          "primaryKey": false,
          "notNull": true
        },
        "pr_id": {
          "name": "pr_id",
          "type": "uuid",
          "primaryKey": false,
          "notNull": false
        },
        "status": {
          "name": "status",
          "type": "purchase_order_status",
          "typeSchema": "public",
          "primaryKey": false,
          "notNull": true,
          "default": "'DRAFT'"
        },
        "created_by_user_id": {
          "name": "created_by_user_id",
          "type": "uuid",
          "primaryKey": false,
          "notNull": true
        },
        "notes": {
          "name": "notes",
          "type": "text",
          "primaryKey": false,
          "notNull": false
        },
        "created_at": {
          "name": "created_at",
          "type": "timestamp with time zone",
          "primaryKey": false,
          "notNull": true,
          "default": "now()"
        },
        "updated_at": {
          "name": "updated_at",
          "type": "timestamp with time zone",
          "primaryKey": false,
          "notNull": true,
          "default": "now()"
        }
      },
      "indexes": {},
      "foreignKeys": {
        "purchase_order_supplier_id_supplier_id_fk": {
          "name": "purchase_order_supplier_id_supplier_id_fk",
          "tableFrom": "purchase_order",
          "tableTo": "supplier",
          "columnsFrom": [
            "supplier_id"
          ],
          "columnsTo": [
            "id"
          ],
          "onDelete": "no action",
          "onUpdate": "no action"
        },
        "purchase_order_pr_id_purchase_request_id_fk": {
          "name": "purchase_order_pr_id_purchase_request_id_fk",
          "tableFrom": "purchase_order",
          "tableTo": "purchase_request",
          "columnsFrom": [
            "pr_id"
          ],
          "columnsTo": [
            "id"
          ],
          "onDelete": "no action",
          "onUpdate": "no action"
        },
        "purchase_order_created_by_user_id_user_id_fk": {
          "name": "purchase_order_created_by_user_id_user_id_fk",
          "tableFrom": "purchase_order",
          "tableTo": "user",
          "columnsFrom": [
            "created_by_user_id"
          ],
          "columnsTo": [
            "id"
          ],
          "onDelete": "no action",
          "onUpdate": "no action"
        }
      },
      "compositePrimaryKeys": {},
      "uniqueConstraints": {
        "purchase_order_po_no_unique": {
          "name": "purchase_order_po_no_unique",
          "nullsNotDistinct": false,
          "columns": [
            "po_no"
          ]
        }
      },
      "policies": {},
      "checkConstraints": {},
      "isRLSEnabled": false
    },
    "public.purchase_request_line": {
      "name": "purchase_request_line",
      "schema": "",
      "columns": {
        "id": {
          "name": "id",
          "type": "uuid",
          "primaryKey": true,
          "notNull": true,
          "default": "gen_random_uuid()"
        },
        "pr_id": {
          "name": "pr_id",
          "type": "uuid",
          "primaryKey": false,
          "notNull": true
        },
        "ingredient_id": {
          "name": "ingredient_id",
          "type": "uuid",
          "primaryKey": false,
          "notNull": true
        },
        "quantity": {
          "name": "quantity",
          "type": "numeric(14, 4)",
          "primaryKey": false,
          "notNull": true
        },
        "est_unit_cost": {
          "name": "est_unit_cost",
          "type": "numeric(14, 4)",
          "primaryKey": false,
          "notNull": true,
          "default": "'0'"
        }
      },
      "indexes": {},
      "foreignKeys": {
        "purchase_request_line_pr_id_purchase_request_id_fk": {
          "name": "purchase_request_line_pr_id_purchase_request_id_fk",
          "tableFrom": "purchase_request_line",
          "tableTo": "purchase_request",
          "columnsFrom": [
            "pr_id"
          ],
          "columnsTo": [
            "id"
          ],
          "onDelete": "no action",
          "onUpdate": "no action"
        },
        "purchase_request_line_ingredient_id_ingredient_id_fk": {
          "name": "purchase_request_line_ingredient_id_ingredient_id_fk",
          "tableFrom": "purchase_request_line",
          "tableTo": "ingredient",
          "columnsFrom": [
            "ingredient_id"
          ],
          "columnsTo": [
            "id"
          ],
          "onDelete": "no action",
          "onUpdate": "no action"
        }
      },
      "compositePrimaryKeys": {},
      "uniqueConstraints": {},
      "policies": {},
      "checkConstraints": {},
      "isRLSEnabled": false
    },
    "public.purchase_request": {
      "name": "purchase_request",
      "schema": "",
      "columns": {
        "id": {
          "name": "id",
          "type": "uuid",
          "primaryKey": true,
          "notNull": true,
          "default": "gen_random_uuid()"
        },
        "pr_no": {
          "name": "pr_no",
          "type": "text",
          "primaryKey": false,
          "notNull": true
        },
        "department": {
          "name": "department",
          "type": "department",
          "typeSchema": "public",
          "primaryKey": false,
          "notNull": true
        },
        "status": {
          "name": "status",
          "type": "purchase_request_status",
          "typeSchema": "public",
          "primaryKey": false,
          "notNull": true,
          "default": "'DRAFT'"
        },
        "requested_by_user_id": {
          "name": "requested_by_user_id",
          "type": "uuid",
          "primaryKey": false,
          "notNull": true
        },
        "approved_by_user_id": {
          "name": "approved_by_user_id",
          "type": "uuid",
          "primaryKey": false,
          "notNull": false
        },
        "notes": {
          "name": "notes",
          "type": "text",
          "primaryKey": false,
          "notNull": false
        },
        "created_at": {
          "name": "created_at",
          "type": "timestamp with time zone",
          "primaryKey": false,
          "notNull": true,
          "default": "now()"
        },
        "updated_at": {
          "name": "updated_at",
          "type": "timestamp with time zone",
          "primaryKey": false,
          "notNull": true,
          "default": "now()"
        }
      },
      "indexes": {},
      "foreignKeys": {
        "purchase_request_requested_by_user_id_user_id_fk": {
          "name": "purchase_request_requested_by_user_id_user_id_fk",
          "tableFrom": "purchase_request",
          "tableTo": "user",
          "columnsFrom": [
            "requested_by_user_id"
          ],
          "columnsTo": [
            "id"
          ],
          "onDelete": "no action",
          "onUpdate": "no action"
        },
        "purchase_request_approved_by_user_id_user_id_fk": {
          "name": "purchase_request_approved_by_user_id_user_id_fk",
          "tableFrom": "purchase_request",
          "tableTo": "user",
          "columnsFrom": [
            "approved_by_user_id"
          ],
          "columnsTo": [
            "id"
          ],
          "onDelete": "no action",
          "onUpdate": "no action"
        }
      },
      "compositePrimaryKeys": {},
      "uniqueConstraints": {
        "purchase_request_pr_no_unique": {
          "name": "purchase_request_pr_no_unique",
          "nullsNotDistinct": false,
          "columns": [
            "pr_no"
          ]
        }
      },
      "policies": {},
      "checkConstraints": {},
      "isRLSEnabled": false
    },
    "public.receiving_report_line": {
      "name": "receiving_report_line",
      "schema": "",
      "columns": {
        "id": {
          "name": "id",
          "type": "uuid",
          "primaryKey": true,
          "notNull": true,
          "default": "gen_random_uuid()"
        },
        "rr_id": {
          "name": "rr_id",
          "type": "uuid",
          "primaryKey": false,
          "notNull": true
        },
        "po_line_id": {
          "name": "po_line_id",
          "type": "uuid",
          "primaryKey": false,
          "notNull": true
        },
        "ingredient_id": {
          "name": "ingredient_id",
          "type": "uuid",
          "primaryKey": false,
          "notNull": true
        },
        "qty_received": {
          "name": "qty_received",
          "type": "numeric(14, 4)",
          "primaryKey": false,
          "notNull": true
        }
      },
      "indexes": {},
      "foreignKeys": {
        "receiving_report_line_rr_id_receiving_report_id_fk": {
          "name": "receiving_report_line_rr_id_receiving_report_id_fk",
          "tableFrom": "receiving_report_line",
          "tableTo": "receiving_report",
          "columnsFrom": [
            "rr_id"
          ],
          "columnsTo": [
            "id"
          ],
          "onDelete": "no action",
          "onUpdate": "no action"
        },
        "receiving_report_line_po_line_id_purchase_order_line_id_fk": {
          "name": "receiving_report_line_po_line_id_purchase_order_line_id_fk",
          "tableFrom": "receiving_report_line",
          "tableTo": "purchase_order_line",
          "columnsFrom": [
            "po_line_id"
          ],
          "columnsTo": [
            "id"
          ],
          "onDelete": "no action",
          "onUpdate": "no action"
        },
        "receiving_report_line_ingredient_id_ingredient_id_fk": {
          "name": "receiving_report_line_ingredient_id_ingredient_id_fk",
          "tableFrom": "receiving_report_line",
          "tableTo": "ingredient",
          "columnsFrom": [
            "ingredient_id"
          ],
          "columnsTo": [
            "id"
          ],
          "onDelete": "no action",
          "onUpdate": "no action"
        }
      },
      "compositePrimaryKeys": {},
      "uniqueConstraints": {},
      "policies": {},
      "checkConstraints": {},
      "isRLSEnabled": false
    },
    "public.receiving_report": {
      "name": "receiving_report",
      "schema": "",
      "columns": {
        "id": {
          "name": "id",
          "type": "uuid",
          "primaryKey": true,
          "notNull": true,
          "default": "gen_random_uuid()"
        },
        "rr_no": {
          "name": "rr_no",
          "type": "text",
          "primaryKey": false,
          "notNull": true
        },
        "po_id": {
          "name": "po_id",
          "type": "uuid",
          "primaryKey": false,
          "notNull": true
        },
        "warehouse_id": {
          "name": "warehouse_id",
          "type": "uuid",
          "primaryKey": false,
          "notNull": true
        },
        "received_by_user_id": {
          "name": "received_by_user_id",
          "type": "uuid",
          "primaryKey": false,
          "notNull": true
        },
        "notes": {
          "name": "notes",
          "type": "text",
          "primaryKey": false,
          "notNull": false
        },
        "created_at": {
          "name": "created_at",
          "type": "timestamp with time zone",
          "primaryKey": false,
          "notNull": true,
          "default": "now()"
        }
      },
      "indexes": {},
      "foreignKeys": {
        "receiving_report_po_id_purchase_order_id_fk": {
          "name": "receiving_report_po_id_purchase_order_id_fk",
          "tableFrom": "receiving_report",
          "tableTo": "purchase_order",
          "columnsFrom": [
            "po_id"
          ],
          "columnsTo": [
            "id"
          ],
          "onDelete": "no action",
          "onUpdate": "no action"
        },
        "receiving_report_warehouse_id_warehouse_id_fk": {
          "name": "receiving_report_warehouse_id_warehouse_id_fk",
          "tableFrom": "receiving_report",
          "tableTo": "warehouse",
          "columnsFrom": [
            "warehouse_id"
          ],
          "columnsTo": [
            "id"
          ],
          "onDelete": "no action",
          "onUpdate": "no action"
        },
        "receiving_report_received_by_user_id_user_id_fk": {
          "name": "receiving_report_received_by_user_id_user_id_fk",
          "tableFrom": "receiving_report",
          "tableTo": "user",
          "columnsFrom": [
            "received_by_user_id"
          ],
          "columnsTo": [
            "id"
          ],
          "onDelete": "no action",
          "onUpdate": "no action"
        }
      },
      "compositePrimaryKeys": {},
      "uniqueConstraints": {
        "receiving_report_rr_no_unique": {
          "name": "receiving_report_rr_no_unique",
          "nullsNotDistinct": false,
          "columns": [
            "rr_no"
          ]
        }
      },
      "policies": {},
      "checkConstraints": {},
      "isRLSEnabled": false
    },
    "public.recipe_line": {
      "name": "recipe_line",
      "schema": "",
      "columns": {
        "id": {
          "name": "id",
          "type": "uuid",
          "primaryKey": true,
          "notNull": true,
          "default": "gen_random_uuid()"
        },
        "menu_item_id": {
          "name": "menu_item_id",
          "type": "uuid",
          "primaryKey": false,
          "notNull": true
        },
        "ingredient_id": {
          "name": "ingredient_id",
          "type": "uuid",
          "primaryKey": false,
          "notNull": true
        },
        "portion_qty": {
          "name": "portion_qty",
          "type": "numeric(14, 4)",
          "primaryKey": false,
          "notNull": true
        },
        "unit": {
          "name": "unit",
          "type": "text",
          "primaryKey": false,
          "notNull": true
        }
      },
      "indexes": {},
      "foreignKeys": {
        "recipe_line_menu_item_id_menu_item_id_fk": {
          "name": "recipe_line_menu_item_id_menu_item_id_fk",
          "tableFrom": "recipe_line",
          "tableTo": "menu_item",
          "columnsFrom": [
            "menu_item_id"
          ],
          "columnsTo": [
            "id"
          ],
          "onDelete": "no action",
          "onUpdate": "no action"
        },
        "recipe_line_ingredient_id_ingredient_id_fk": {
          "name": "recipe_line_ingredient_id_ingredient_id_fk",
          "tableFrom": "recipe_line",
          "tableTo": "ingredient",
          "columnsFrom": [
            "ingredient_id"
          ],
          "columnsTo": [
            "id"
          ],
          "onDelete": "no action",
          "onUpdate": "no action"
        }
      },
      "compositePrimaryKeys": {},
      "uniqueConstraints": {},
      "policies": {},
      "checkConstraints": {},
      "isRLSEnabled": false
    },
    "public.stock_ledger_entry": {
      "name": "stock_ledger_entry",
      "schema": "",
      "columns": {
        "id": {
          "name": "id",
          "type": "uuid",
          "primaryKey": true,
          "notNull": true,
          "default": "gen_random_uuid()"
        },
        "source_module": {
          "name": "source_module",
          "type": "stock_ledger_source_module",
          "typeSchema": "public",
          "primaryKey": false,
          "notNull": true
        },
        "source_document_no": {
          "name": "source_document_no",
          "type": "text",
          "primaryKey": false,
          "notNull": true
        },
        "source_line_no": {
          "name": "source_line_no",
          "type": "text",
          "primaryKey": false,
          "notNull": false
        },
        "ingredient_id": {
          "name": "ingredient_id",
          "type": "uuid",
          "primaryKey": false,
          "notNull": true
        },
        "warehouse_id": {
          "name": "warehouse_id",
          "type": "uuid",
          "primaryKey": false,
          "notNull": true
        },
        "movement_type": {
          "name": "movement_type",
          "type": "stock_ledger_movement_type",
          "typeSchema": "public",
          "primaryKey": false,
          "notNull": true
        },
        "quantity": {
          "name": "quantity",
          "type": "numeric(14, 4)",
          "primaryKey": false,
          "notNull": true
        },
        "unit_cost": {
          "name": "unit_cost",
          "type": "numeric(14, 4)",
          "primaryKey": false,
          "notNull": true,
          "default": "'0'"
        },
        "posted_at": {
          "name": "posted_at",
          "type": "timestamp with time zone",
          "primaryKey": false,
          "notNull": true,
          "default": "now()"
        },
        "encoder_user_id": {
          "name": "encoder_user_id",
          "type": "uuid",
          "primaryKey": false,
          "notNull": false
        },
        "metadata": {
          "name": "metadata",
          "type": "jsonb",
          "primaryKey": false,
          "notNull": false
        }
      },
      "indexes": {
        "stock_ledger_source_unique": {
          "name": "stock_ledger_source_unique",
          "columns": [
            {
              "expression": "source_module",
              "isExpression": false,
              "asc": true,
              "nulls": "last"
            },
            {
              "expression": "source_document_no",
              "isExpression": false,
              "asc": true,
              "nulls": "last"
            },
            {
              "expression": "source_line_no",
              "isExpression": false,
              "asc": true,
              "nulls": "last"
            }
          ],
          "isUnique": true,
          "concurrently": false,
          "method": "btree",
          "with": {}
        }
      },
      "foreignKeys": {
        "stock_ledger_entry_ingredient_id_ingredient_id_fk": {
          "name": "stock_ledger_entry_ingredient_id_ingredient_id_fk",
          "tableFrom": "stock_ledger_entry",
          "tableTo": "ingredient",
          "columnsFrom": [
            "ingredient_id"
          ],
          "columnsTo": [
            "id"
          ],
          "onDelete": "no action",
          "onUpdate": "no action"
        },
        "stock_ledger_entry_warehouse_id_warehouse_id_fk": {
          "name": "stock_ledger_entry_warehouse_id_warehouse_id_fk",
          "tableFrom": "stock_ledger_entry",
          "tableTo": "warehouse",
          "columnsFrom": [
            "warehouse_id"
          ],
          "columnsTo": [
            "id"
          ],
          "onDelete": "no action",
          "onUpdate": "no action"
        },
        "stock_ledger_entry_encoder_user_id_user_id_fk": {
          "name": "stock_ledger_entry_encoder_user_id_user_id_fk",
          "tableFrom": "stock_ledger_entry",
          "tableTo": "user",
          "columnsFrom": [
            "encoder_user_id"
          ],
          "columnsTo": [
            "id"
          ],
          "onDelete": "no action",
          "onUpdate": "no action"
        }
      },
      "compositePrimaryKeys": {},
      "uniqueConstraints": {},
      "policies": {},
      "checkConstraints": {},
      "isRLSEnabled": false
    },
    "public.supplier_item": {
      "name": "supplier_item",
      "schema": "",
      "columns": {
        "id": {
          "name": "id",
          "type": "uuid",
          "primaryKey": true,
          "notNull": true,
          "default": "gen_random_uuid()"
        },
        "supplier_id": {
          "name": "supplier_id",
          "type": "uuid",
          "primaryKey": false,
          "notNull": true
        },
        "ingredient_id": {
          "name": "ingredient_id",
          "type": "uuid",
          "primaryKey": false,
          "notNull": true
        },
        "supplier_sku": {
          "name": "supplier_sku",
          "type": "text",
          "primaryKey": false,
          "notNull": false
        },
        "last_unit_cost": {
          "name": "last_unit_cost",
          "type": "numeric(14, 4)",
          "primaryKey": false,
          "notNull": true,
          "default": "'0'"
        }
      },
      "indexes": {
        "supplier_item_unique": {
          "name": "supplier_item_unique",
          "columns": [
            {
              "expression": "supplier_id",
              "isExpression": false,
              "asc": true,
              "nulls": "last"
            },
            {
              "expression": "ingredient_id",
              "isExpression": false,
              "asc": true,
              "nulls": "last"
            }
          ],
          "isUnique": true,
          "concurrently": false,
          "method": "btree",
          "with": {}
        }
      },
      "foreignKeys": {
        "supplier_item_supplier_id_supplier_id_fk": {
          "name": "supplier_item_supplier_id_supplier_id_fk",
          "tableFrom": "supplier_item",
          "tableTo": "supplier",
          "columnsFrom": [
            "supplier_id"
          ],
          "columnsTo": [
            "id"
          ],
          "onDelete": "no action",
          "onUpdate": "no action"
        },
        "supplier_item_ingredient_id_ingredient_id_fk": {
          "name": "supplier_item_ingredient_id_ingredient_id_fk",
          "tableFrom": "supplier_item",
          "tableTo": "ingredient",
          "columnsFrom": [
            "ingredient_id"
          ],
          "columnsTo": [
            "id"
          ],
          "onDelete": "no action",
          "onUpdate": "no action"
        }
      },
      "compositePrimaryKeys": {},
      "uniqueConstraints": {},
      "policies": {},
      "checkConstraints": {},
      "isRLSEnabled": false
    },
    "public.supplier": {
      "name": "supplier",
      "schema": "",
      "columns": {
        "id": {
          "name": "id",
          "type": "uuid",
          "primaryKey": true,
          "notNull": true,
          "default": "gen_random_uuid()"
        },
        "code": {
          "name": "code",
          "type": "text",
          "primaryKey": false,
          "notNull": true
        },
        "name": {
          "name": "name",
          "type": "text",
          "primaryKey": false,
          "notNull": true
        },
        "contact_name": {
          "name": "contact_name",
          "type": "text",
          "primaryKey": false,
          "notNull": false
        },
        "contact_phone": {
          "name": "contact_phone",
          "type": "text",
          "primaryKey": false,
          "notNull": false
        },
        "email": {
          "name": "email",
          "type": "text",
          "primaryKey": false,
          "notNull": false
        },
        "address": {
          "name": "address",
          "type": "text",
          "primaryKey": false,
          "notNull": false
        },
        "payment_term_days": {
          "name": "payment_term_days",
          "type": "integer",
          "primaryKey": false,
          "notNull": true,
          "default": 0
        },
        "is_active": {
          "name": "is_active",
          "type": "boolean",
          "primaryKey": false,
          "notNull": true,
          "default": true
        },
        "created_at": {
          "name": "created_at",
          "type": "timestamp with time zone",
          "primaryKey": false,
          "notNull": true,
          "default": "now()"
        },
        "updated_at": {
          "name": "updated_at",
          "type": "timestamp with time zone",
          "primaryKey": false,
          "notNull": true,
          "default": "now()"
        }
      },
      "indexes": {},
      "foreignKeys": {},
      "compositePrimaryKeys": {},
      "uniqueConstraints": {
        "supplier_code_unique": {
          "name": "supplier_code_unique",
          "nullsNotDistinct": false,
          "columns": [
            "code"
          ]
        }
      },
      "policies": {},
      "checkConstraints": {},
      "isRLSEnabled": false
    },
    "public.user_brand": {
      "name": "user_brand",
      "schema": "",
      "columns": {
        "id": {
          "name": "id",
          "type": "uuid",
          "primaryKey": true,
          "notNull": true,
          "default": "gen_random_uuid()"
        },
        "user_id": {
          "name": "user_id",
          "type": "uuid",
          "primaryKey": false,
          "notNull": true
        },
        "brand_id": {
          "name": "brand_id",
          "type": "uuid",
          "primaryKey": false,
          "notNull": true
        }
      },
      "indexes": {
        "user_brand_user_brand_unique": {
          "name": "user_brand_user_brand_unique",
          "columns": [
            {
              "expression": "user_id",
              "isExpression": false,
              "asc": true,
              "nulls": "last"
            },
            {
              "expression": "brand_id",
              "isExpression": false,
              "asc": true,
              "nulls": "last"
            }
          ],
          "isUnique": true,
          "concurrently": false,
          "method": "btree",
          "with": {}
        }
      },
      "foreignKeys": {
        "user_brand_user_id_user_id_fk": {
          "name": "user_brand_user_id_user_id_fk",
          "tableFrom": "user_brand",
          "tableTo": "user",
          "columnsFrom": [
            "user_id"
          ],
          "columnsTo": [
            "id"
          ],
          "onDelete": "no action",
          "onUpdate": "no action"
        },
        "user_brand_brand_id_brand_id_fk": {
          "name": "user_brand_brand_id_brand_id_fk",
          "tableFrom": "user_brand",
          "tableTo": "brand",
          "columnsFrom": [
            "brand_id"
          ],
          "columnsTo": [
            "id"
          ],
          "onDelete": "no action",
          "onUpdate": "no action"
        }
      },
      "compositePrimaryKeys": {},
      "uniqueConstraints": {},
      "policies": {},
      "checkConstraints": {},
      "isRLSEnabled": false
    },
    "public.user_session": {
      "name": "user_session",
      "schema": "",
      "columns": {
        "id": {
          "name": "id",
          "type": "uuid",
          "primaryKey": true,
          "notNull": true,
          "default": "gen_random_uuid()"
        },
        "user_id": {
          "name": "user_id",
          "type": "uuid",
          "primaryKey": false,
          "notNull": true
        },
        "login_at": {
          "name": "login_at",
          "type": "timestamp with time zone",
          "primaryKey": false,
          "notNull": true,
          "default": "now()"
        },
        "logout_at": {
          "name": "logout_at",
          "type": "timestamp with time zone",
          "primaryKey": false,
          "notNull": false
        },
        "ip": {
          "name": "ip",
          "type": "text",
          "primaryKey": false,
          "notNull": false
        },
        "user_agent": {
          "name": "user_agent",
          "type": "text",
          "primaryKey": false,
          "notNull": false
        }
      },
      "indexes": {},
      "foreignKeys": {
        "user_session_user_id_user_id_fk": {
          "name": "user_session_user_id_user_id_fk",
          "tableFrom": "user_session",
          "tableTo": "user",
          "columnsFrom": [
            "user_id"
          ],
          "columnsTo": [
            "id"
          ],
          "onDelete": "no action",
          "onUpdate": "no action"
        }
      },
      "compositePrimaryKeys": {},
      "uniqueConstraints": {},
      "policies": {},
      "checkConstraints": {},
      "isRLSEnabled": false
    },
    "public.user": {
      "name": "user",
      "schema": "",
      "columns": {
        "id": {
          "name": "id",
          "type": "uuid",
          "primaryKey": true,
          "notNull": true,
          "default": "gen_random_uuid()"
        },
        "name": {
          "name": "name",
          "type": "text",
          "primaryKey": false,
          "notNull": true
        },
        "email": {
          "name": "email",
          "type": "text",
          "primaryKey": false,
          "notNull": true
        },
        "password_hash": {
          "name": "password_hash",
          "type": "text",
          "primaryKey": false,
          "notNull": true
        },
        "role": {
          "name": "role",
          "type": "role",
          "typeSchema": "public",
          "primaryKey": false,
          "notNull": true
        },
        "created_at": {
          "name": "created_at",
          "type": "timestamp with time zone",
          "primaryKey": false,
          "notNull": true,
          "default": "now()"
        },
        "updated_at": {
          "name": "updated_at",
          "type": "timestamp with time zone",
          "primaryKey": false,
          "notNull": true,
          "default": "now()"
        }
      },
      "indexes": {},
      "foreignKeys": {},
      "compositePrimaryKeys": {},
      "uniqueConstraints": {
        "user_email_unique": {
          "name": "user_email_unique",
          "nullsNotDistinct": false,
          "columns": [
            "email"
          ]
        }
      },
      "policies": {},
      "checkConstraints": {},
      "isRLSEnabled": false
    },
    "public.warehouse": {
      "name": "warehouse",
      "schema": "",
      "columns": {
        "id": {
          "name": "id",
          "type": "uuid",
          "primaryKey": true,
          "notNull": true,
          "default": "gen_random_uuid()"
        },
        "location_id": {
          "name": "location_id",
          "type": "uuid",
          "primaryKey": false,
          "notNull": true
        },
        "type": {
          "name": "type",
          "type": "warehouse_type",
          "typeSchema": "public",
          "primaryKey": false,
          "notNull": true
        }
      },
      "indexes": {
        "warehouse_location_type_unique": {
          "name": "warehouse_location_type_unique",
          "columns": [
            {
              "expression": "location_id",
              "isExpression": false,
              "asc": true,
              "nulls": "last"
            },
            {
              "expression": "type",
              "isExpression": false,
              "asc": true,
              "nulls": "last"
            }
          ],
          "isUnique": true,
          "concurrently": false,
          "method": "btree",
          "with": {}
        }
      },
      "foreignKeys": {
        "warehouse_location_id_location_id_fk": {
          "name": "warehouse_location_id_location_id_fk",
          "tableFrom": "warehouse",
          "tableTo": "location",
          "columnsFrom": [
            "location_id"
          ],
          "columnsTo": [
            "id"
          ],
          "onDelete": "no action",
          "onUpdate": "no action"
        }
      },
      "compositePrimaryKeys": {},
      "uniqueConstraints": {},
      "policies": {},
      "checkConstraints": {},
      "isRLSEnabled": false
    }
  },
  "enums": {
    "public.aggregator": {
      "name": "aggregator",
      "schema": "public",
      "values": [
        "FOODPANDA",
        "GRABFOOD",
        "OTHER"
      ]
    },
    "public.attendance_type": {
      "name": "attendance_type",
      "schema": "public",
      "values": [
        "TIME_IN",
        "TIME_OUT"
      ]
    },
    "public.availability": {
      "name": "availability",
      "schema": "public",
      "values": [
        "AVAILABLE",
        "PAUSED",
        "SOLD_OUT"
      ]
    },
    "public.department": {
      "name": "department",
      "schema": "public",
      "values": [
        "KITCHEN",
        "WAREHOUSE",
        "PURCHASING",
        "SALES",
        "PRODUCTION",
        "QA",
        "ACCOUNTING",
        "ADMIN"
      ]
    },
    "public.employee_status": {
      "name": "employee_status",
      "schema": "public",
      "values": [
        "ACTIVE",
        "INACTIVE"
      ]
    },
    "public.ito_status": {
      "name": "ito_status",
      "schema": "public",
      "values": [
        "REQUESTED",
        "CONFIRMED",
        "CANCELLED"
      ]
    },
    "public.location_status": {
      "name": "location_status",
      "schema": "public",
      "values": [
        "ACTIVE",
        "INACTIVE"
      ]
    },
    "public.order_status": {
      "name": "order_status",
      "schema": "public",
      "values": [
        "NEW",
        "PREPARING",
        "READY",
        "COMPLETED",
        "CANCELLED"
      ]
    },
    "public.print_job_status": {
      "name": "print_job_status",
      "schema": "public",
      "values": [
        "PENDING",
        "PRINTED",
        "FAILED"
      ]
    },
    "public.printer_connection": {
      "name": "printer_connection",
      "schema": "public",
      "values": [
        "USB",
        "NETWORK",
        "SERIAL"
      ]
    },
    "public.printer_status": {
      "name": "printer_status",
      "schema": "public",
      "values": [
        "ONLINE",
        "OFFLINE",
        "ERROR"
      ]
    },
    "public.purchase_order_status": {
      "name": "purchase_order_status",
      "schema": "public",
      "values": [
        "DRAFT",
        "SENT",
        "PARTIAL",
        "RECEIVED",
        "CANCELLED"
      ]
    },
    "public.purchase_request_status": {
      "name": "purchase_request_status",
      "schema": "public",
      "values": [
        "DRAFT",
        "SUBMITTED",
        "APPROVED",
        "REJECTED",
        "CLOSED"
      ]
    },
    "public.role": {
      "name": "role",
      "schema": "public",
      "values": [
        "SUPER_ADMIN",
        "BRAND_MANAGER",
        "KITCHEN_STAFF",
        "WAREHOUSE",
        "SUPPLIER_COORDINATOR",
        "ACCOUNTANT",
        "RIDER"
      ]
    },
    "public.stock_ledger_movement_type": {
      "name": "stock_ledger_movement_type",
      "schema": "public",
      "values": [
        "IN",
        "OUT"
      ]
    },
    "public.stock_ledger_source_module": {
      "name": "stock_ledger_source_module",
      "schema": "public",
      "values": [
        "RECEIVE",
        "ITO",
        "ORDER_DEDUCTION",
        "ADJUSTMENT",
        "RESTOCK"
      ]
    },
    "public.warehouse_type": {
      "name": "warehouse_type",
      "schema": "public",
      "values": [
        "MAIN",
        "KITCHEN"
      ]
    }
  },
  "schemas": {},
  "sequences": {},
  "roles": {},
  "policies": {},
  "views": {},
  "_meta": {
    "columns": {},
    "schemas": {},
    "tables": {}
  }
}